tkitScrapyMongoPipeline/__init__.py
tkitScrapyMongoPipeline/pipelines.py
tkitScrapyMongoPipeline-0.0.0.116522771.dist-info/LICENSE
tkitScrapyMongoPipeline-0.0.0.116522771.dist-info/METADATA
tkitScrapyMongoPipeline-0.0.0.116522771.dist-info/WHEEL
tkitScrapyMongoPipeline-0.0.0.116522771.dist-info/top_level.txt
tkitScrapyMongoPipeline-0.0.0.116522771.dist-info/RECORD
