Metadata-Version: 2.1
Name: tkitScrapyMongoPipeline
Version: 0.0.0.116522771
Summary: tkitScrapyMongoPipeline,
Home-page: http://docs.terrychan.org/tkit-lr-pytorch/
Author: Terry Chan
Author-email: napoler2008@gmail.com
License: UNKNOWN
Platform: UNKNOWN
License-File: LICENSE
Requires-Dist: pymongo (==4.1.1)
Requires-Dist: Scrapy (>=2.6.1)
